KOMORANPy/__init__.py
KOMORANPy/common/__init__.py
KOMORANPy/common/dictionary.py
KOMORANPy/common/grammar.py
KOMORANPy/common/ahocorasick/__init__.py
KOMORANPy/common/ahocorasick/ahocorasick_dictionary.py
KOMORANPy/common/ahocorasick/ahocorasick_node.py
KOMORANPy/common/irregular/__init__.py
KOMORANPy/common/irregular/irregular_node.py
KOMORANPy/common/irregular/irregular_trie.py
KOMORANPy/constant/FILENAME.py
KOMORANPy/constant/SYMBOL.py
KOMORANPy/constant/__init__.py
KOMORANPy/core/__init__.py
KOMORANPy/core/komoran.py
KOMORANPy/parser/__init__.py
KOMORANPy/parser/corpus_parser.py
KOMORANPy/parser/irregular_parser.py
KOMORANPy/parser/korean_unit_parser.py
KOMORANPy/parser/problem_answer_info.py
KOMORANPy/test/__init__.py
KOMORANPy/test/stress_test.py
KOMORANPy/test/stress_test_with_multiprocessing.py
KOMORANPy/training/__init__.py
KOMORANPy/training/corpus_builder.py
KOMORANPy/training/model_builder.py
KOMORANPy/training/trainer.py
KOMORANPy/training/model/__init__.py
KOMORANPy/training/model/observation.py
KOMORANPy/training/model/pos_table.py
KOMORANPy/training/model/transition.py
KOMORANPy/utils/__init__.py
KOMORANPy/utils/string_util.py
komoranPi-0.0.1.dist-info/LICENSE
komoranPi-0.0.1.dist-info/METADATA
komoranPi-0.0.1.dist-info/WHEEL
komoranPi-0.0.1.dist-info/top_level.txt
komoranPi-0.0.1.dist-info/RECORD
